deda_bin/__init__.py
deda_bin/deda_anonmask_apply.py
deda_bin/deda_anonmask_create.py
deda_bin/deda_clean_document.py
deda_bin/deda_compare_prints.py
deda_bin/deda_create_dots.py
deda_bin/deda_parse_print.py
deda_gui/__init__.py
deda_gui/deda_gui.py
deda_gui/web/comparison.html
deda_gui/web/contact.html
deda_gui/web/forensic.html
deda_gui/web/generate.html
deda_gui/web/index.html
deda_gui/web/printanon.html
deda_gui/web/printanon2.html
deda_gui/web/scananon.html
deda_gui/web/sidebar.html
deda_gui/web/css/bootstrap-datetimepicker.min.css
deda_gui/web/css/bootstrap.min.css
deda_gui/web/css/dedastyle.css
deda_gui/web/css/fontawesome-all.css
deda_gui/web/css/fontawesome.min.css
deda_gui/web/de/comparison.html
deda_gui/web/de/contact.html
deda_gui/web/de/forensic.html
deda_gui/web/de/generate.html
deda_gui/web/de/index.html
deda_gui/web/de/printanon.html
deda_gui/web/de/printanon2.html
deda_gui/web/de/scananon.html
deda_gui/web/de/sidebar.html
deda_gui/web/js/bootstrap-datetimepicker.min.js
deda_gui/web/js/bootstrap.bundle.min.js
deda_gui/web/js/bootstrap.min.js
deda_gui/web/js/deda.js
deda_gui/web/js/dom-to-image.min.js
deda_gui/web/js/jquery.min.js
deda_gui/web/js/jspdf.min.js
deda_gui/web/js/jspdf.plugin.autotable.min.js
deda_gui/web/js/popper.min.js
deda_gui/web/misc/calibration.pdf
deda_gui/web/misc/calibration.png
deda_gui/web/misc/calibration.ps
deda_gui/web/misc/logo.png
deda_gui/web/misc/x-y.png
deda_gui/web/webfonts/fa-brands-400.eot
deda_gui/web/webfonts/fa-brands-400.svg
deda_gui/web/webfonts/fa-brands-400.ttf
deda_gui/web/webfonts/fa-brands-400.woff
deda_gui/web/webfonts/fa-brands-400.woff2
deda_gui/web/webfonts/fa-regular-400.eot
deda_gui/web/webfonts/fa-regular-400.svg
deda_gui/web/webfonts/fa-regular-400.ttf
deda_gui/web/webfonts/fa-regular-400.woff
deda_gui/web/webfonts/fa-regular-400.woff2
deda_gui/web/webfonts/fa-solid-900.eot
deda_gui/web/webfonts/fa-solid-900.svg
deda_gui/web/webfonts/fa-solid-900.ttf
deda_gui/web/webfonts/fa-solid-900.woff
deda-2.0b4.dist-info/LICENSE
deda-2.0b4.dist-info/METADATA
deda-2.0b4.dist-info/WHEEL
deda-2.0b4.dist-info/entry_points.txt
deda-2.0b4.dist-info/top_level.txt
deda-2.0b4.dist-info/RECORD
