Metadata-Version: 2.1
Name: deda
Version: 2.0b4
Summary: tracking Dots Extraction, Decoding and Anonymisation toolkit
Home-page: https://github.com/dfd-tud/deda
Author: Timo Richter and Stephan Escher
Author-email: timo.juez@gmail.com
License: GNU General Public License v3 or later (GPLv3+)
Classifier: Programming Language :: Python :: 3
Classifier: License :: OSI Approved :: GNU General Public License v3 or later (GPLv3+)
Classifier: Topic :: Scientific/Engineering :: Information Analysis
Classifier: Topic :: Printing
Requires-Python: >=3.3
License-File: LICENSE
Requires-Dist: numpy
Requires-Dist: opencv-python
Requires-Dist: argparse
Requires-Dist: scipy
Requires-Dist: Pillow
Requires-Dist: PyPDF2
Requires-Dist: reportlab
Requires-Dist: eel
